kptn/__init__.py
kptn/read_config.py
kptn/runner.py
kptn/aws/creds.py
kptn/aws/decider.py
kptn/caching/Hasher.py
kptn/caching/README.md
kptn/caching/TSCacheUtils.py
kptn/caching/TaskStateCache.py
kptn/caching/TaskStateDbClient.py
kptn/caching/__init__.py
kptn/caching/batch.py
kptn/caching/models.py
kptn/caching/prefect.py
kptn/caching/r_imports.py
kptn/caching/submit.py
kptn/caching/vanilla.py
kptn/caching/client/DbClientBase.py
kptn/caching/client/DbClientDDB.py
kptn/caching/client/DbClientSQLite.py
kptn/caching/client/__init__.py
kptn/caching/client/dynamodb/__init__.py
kptn/caching/client/dynamodb/create_subtaskbin.py
kptn/caching/client/dynamodb/create_task.py
kptn/caching/client/dynamodb/create_taskdatabin.py
kptn/caching/client/dynamodb/get_subtaskbins.py
kptn/caching/client/dynamodb/get_task.py
kptn/caching/client/dynamodb/get_taskdata.py
kptn/caching/client/dynamodb/get_tasks.py
kptn/caching/client/dynamodb/set_subtask_time.py
kptn/caching/client/dynamodb/update_task.py
kptn/caching/client/sqlite/__init__.py
kptn/caching/client/sqlite/create_subtaskbin.py
kptn/caching/client/sqlite/create_task.py
kptn/caching/client/sqlite/create_taskdatabin.py
kptn/caching/client/sqlite/schema.md
kptn/cli/__init__.py
kptn/cli/config_validation.py
kptn/cli/decider_bundle.py
kptn/cli/infra_commands.py
kptn/cli/run_aws.py
kptn/cli/task_validation.py
kptn/codegen/__init__.py
kptn/codegen/codegen.py
kptn/codegen/infra_scaffolder.py
kptn/codegen/lib/__init__.py
kptn/codegen/lib/modify_tasks_obj.py
kptn/codegen/lib/setup_jinja_env.py
kptn/codegen/lib/stepfunctions.py
kptn/codegen/templates/prefect/flows.py.jinja
kptn/codegen/templates/prefect/macros.jinja
kptn/codegen/templates/prefect/tasks_init.py.jinja
kptn/codegen/templates/stepfunctions/.gitignore
kptn/codegen/templates/stepfunctions/DOCKER_BUILD.md
kptn/codegen/templates/stepfunctions/README.md.tpl
kptn/codegen/templates/stepfunctions/batch.tf
kptn/codegen/templates/stepfunctions/docker_image.tf
kptn-0.1.12.dist-info/METADATA
kptn-0.1.12.dist-info/WHEEL
kptn-0.1.12.dist-info/entry_points.txt
kptn-0.1.12.dist-info/licenses/LICENSE
kptn-0.1.12.dist-info/RECORD
