Metadata-Version: 2.4
Name: kptn
Version: 0.1.12
Summary: Meta tool for managing and deploying data pipelines.
License-File: LICENSE
Requires-Python: >=3.11
Requires-Dist: jinja2
Requires-Dist: jsonschema==4.21.1
Requires-Dist: pydantic
Requires-Dist: pyyaml
Requires-Dist: requests
Requires-Dist: sqlglot>=26.3.8
Requires-Dist: typer>=0.12.5
Provides-Extra: aws
Requires-Dist: boto3; extra == 'aws'
Provides-Extra: duckdb
Requires-Dist: duckdb; extra == 'duckdb'
Provides-Extra: prefect
Requires-Dist: prefect; extra == 'prefect'
Provides-Extra: web
Requires-Dist: fastapi>=0.116.2; extra == 'web'
Requires-Dist: uvicorn>=0.35.0; extra == 'web'
Requires-Dist: watchfiles; extra == 'web'
